bluesmet/__init__.py
bluesmet/common/__init__.py
bluesmet/common/latlon.py
bluesmet/common/scatter.py
bluesmet/normet/__init__.py
bluesmet/normet/cache.py
bluesmet/normet/combine.py
bluesmet/normet/dataset.py
bluesmet/normet/metengine/__init__.py
bluesmet/normet/metengine/extreme_stats.py
bluesmet/normet/nora3/__init__.py
bluesmet/normet/nora3/arome3km_3hr.py
bluesmet/normet/nora3/mywavewam3km.py
bluesmet/normet/nora3/wave_sub_time.py
bluesmet/normet/norkyst/__init__.py
bluesmet/normet/norkyst/zdepths_his.py
bluesmet-0.4.4.dist-info/LICENSE
bluesmet-0.4.4.dist-info/METADATA
bluesmet-0.4.4.dist-info/WHEEL
bluesmet-0.4.4.dist-info/top_level.txt
bluesmet-0.4.4.dist-info/RECORD
