Metadata-Version: 2.1
Name: bluesmet
Version: 0.4.4
Summary: SFI Blues Metocean Library
Author: SINTEF Ocean
License: MIT
Classifier: Programming Language :: Python :: 3
Classifier: License :: OSI Approved :: MIT License
Requires-Python: >=3.8
License-File: LICENSE
